flake8_fastapi_route_case.py
flake8_fastapi_route_case-0.1.0.dist-info/LICENSE
flake8_fastapi_route_case-0.1.0.dist-info/WHEEL
flake8_fastapi_route_case-0.1.0.dist-info/entry_points.txt
flake8_fastapi_route_case-0.1.0.dist-info/METADATA
flake8_fastapi_route_case-0.1.0.dist-info/RECORD
