Metadata-Version: 2.1
Name: flake8-fastapi-route-case
Version: 0.1.0
Summary: Flake8 extension to check FastAPI routes all use the same case
License: MIT
Author: Harry Lees
Author-email: harry.lees@gmail.com
Requires-Python: >=3.8.1
Classifier: License :: OSI Approved :: MIT License
Classifier: Programming Language :: Python :: 3
Classifier: Programming Language :: Python :: 3.9
Classifier: Programming Language :: Python :: 3.10
Classifier: Programming Language :: Python :: 3.11
Requires-Dist: importlib-metadata (>=6.0.0)
